{
  "generated_utc": "2026-02-18T14:48:10+00:00",
  "total_records": 118396,
  "parts": [
    {
      "path": "docs/db\\srr_records_part000.json",
      "records": 11102
    },
    {
      "path": "docs/db\\srr_records_part001.json",
      "records": 10868
    },
    {
      "path": "docs/db\\srr_records_part002.json",
      "records": 11193
    },
    {
      "path": "docs/db\\srr_records_part003.json",
      "records": 10735
    },
    {
      "path": "docs/db\\srr_records_part004.json",
      "records": 10024
    },
    {
      "path": "docs/db\\srr_records_part005.json",
      "records": 10850
    },
    {
      "path": "docs/db\\srr_records_part006.json",
      "records": 10979
    },
    {
      "path": "docs/db\\srr_records_part007.json",
      "records": 11219
    },
    {
      "path": "docs/db\\srr_records_part008.json",
      "records": 10878
    },
    {
      "path": "docs/db\\srr_records_part009.json",
      "records": 10809
    },
    {
      "path": "docs/db\\srr_records_part010.json",
      "records": 9739
    }
  ],
  "years": [
    2026
  ]
}